README.md
setup.py
image_processing/__init__.py
image_processing/processing/__init__.py
image_processing/processing/combination.py
image_processing/processing/transformation.py
image_processing/utils/__init__.py
image_processing/utils/io.py
image_processing/utils/plot.py
packages_image_processing.egg-info/PKG-INFO
packages_image_processing.egg-info/SOURCES.txt
packages_image_processing.egg-info/dependency_links.txt
packages_image_processing.egg-info/requires.txt
packages_image_processing.egg-info/top_level.txt