Metadata-Version: 2.1
Name: packages_image_processing
Version: 0.0.1
Summary: processamento de imagens
Home-page: https://github.com/SantanaGabriela/image-processing-package
Author: Gabriela
Author-email: cristinagabriela.trajano@gmail.com
Requires-Python: >=3.8
Requires-Dist: setuptools>=40.8.0
Requires-Dist: wheel>=0.36.0
